pyIcingaOSChecks/__init__.py
pyIcingaOSChecks/os/__init__.py
pyIcingaOSChecks/os/diskusage.py
pyIcingaOSChecks/os/load.py
pyIcingaOSChecks/os/memory.py
pyIcingaOSChecks/os/networkstats.py
pyIcingaOSChecks/os/networkstatus.py
pyIcingaOSChecks/os/systemd.py
pyIcingaOSChecks-0.0.1.dist-info/METADATA
pyIcingaOSChecks-0.0.1.dist-info/WHEEL
pyIcingaOSChecks-0.0.1.dist-info/top_level.txt
pyIcingaOSChecks-0.0.1.dist-info/RECORD
