Metadata-Version: 2.1
Name: pyIcingaOSChecks
Version: 0.0.1
Summary: Icinga2 Check OS Checks for pyIcingaFramework
Author: Paul Denning
Keywords: icinga2,nagios
Classifier: Intended Audience :: Developers
Classifier: Programming Language :: Python :: 3
Requires-Dist: pyIcingaFramework
Requires-Dist: psutil
Requires-Dist: dbus-python
